trustymail/__init__.py
trustymail/__main__.py
trustymail/_version.py
trustymail/cli.py
trustymail/domain.py
trustymail/trustymail.py
trustymail-1.2.1.dist-info/licenses/LICENSE
trustymail-1.2.1.dist-info/METADATA
trustymail-1.2.1.dist-info/WHEEL
trustymail-1.2.1.dist-info/entry_points.txt
trustymail-1.2.1.dist-info/top_level.txt
trustymail-1.2.1.dist-info/RECORD
