Metadata-Version: 2.4
Name: trustymail
Version: 1.2.1
Summary: Scan domains and return data based on trustworthy email best practices
Author-email: Cybersecurity and Infrastructure Security Agency <github@cisa.dhs.gov>
License: CC0-1.0
Project-URL: homepage, https://github.com/cisagov/trustymail
Project-URL: issues, https://github.com/cisagov/trustymail/issues
Project-URL: mission, https://www.cisa.gov/cybersecurity
Project-URL: source, https://github.com/cisagov/trustymail
Keywords: email,authentication,STARTTLS
Classifier: Development Status :: 4 - Beta
Classifier: Environment :: Console
Classifier: Intended Audience :: Developers
Classifier: Natural Language :: English
Classifier: Operating System :: OS Independent
Classifier: Programming Language :: Python :: 3
Classifier: Programming Language :: Python :: 3 :: Only
Classifier: Programming Language :: Python :: 3.7
Classifier: Programming Language :: Python :: 3.8
Classifier: Programming Language :: Python :: 3.9
Classifier: Programming Language :: Python :: 3.10
Classifier: Programming Language :: Python :: 3.11
Classifier: Programming Language :: Python :: 3.12
Classifier: Programming Language :: Python :: 3.13
Classifier: Programming Language :: Python :: 3.14
Classifier: Programming Language :: Python :: Implementation :: CPython
Requires-Python: >=3.7
License-File: LICENSE
Requires-Dist: dnspython
Requires-Dist: docopt
Requires-Dist: publicsuffixlist[update]
Requires-Dist: py3dns
Requires-Dist: pyspf
Requires-Dist: requests
Provides-Extra: dev
Requires-Dist: types-docopt; extra == "dev"
Requires-Dist: types-requests; extra == "dev"
Provides-Extra: test
Requires-Dist: coverage; extra == "test"
Requires-Dist: coveralls; extra == "test"
Requires-Dist: pre-commit; extra == "test"
Requires-Dist: pytest-cov; extra == "test"
Requires-Dist: pytest; extra == "test"
Dynamic: license-file
